setup.py
pyaliyun/__init__.py
pyaliyun/test_config.py
pyaliyun.egg-info/PKG-INFO
pyaliyun.egg-info/SOURCES.txt
pyaliyun.egg-info/dependency_links.txt
pyaliyun.egg-info/requires.txt
pyaliyun.egg-info/top_level.txt
pyaliyun/core/__init__.py
pyaliyun/core/account.py
pyaliyun/core/api.py
pyaliyun/core/constant.py
pyaliyun/core/cryptool.py
pyaliyun/core/encoding.py
pyaliyun/core/exception.py
pyaliyun/core/request.py
pyaliyun/core/response.py
pyaliyun/core/services.py
pyaliyun/core/six.py
pyaliyun/core/utils.py
pyaliyun/core/xmltools.py
pyaliyun/mns/__init__.py
pyaliyun/mns/api.py
pyaliyun/oss/__init__.py
pyaliyun/oss/api.py
pyaliyun/oss/request.py