Metadata-Version: 1.1
Name: pyaliyun
Version: 1.0.5.3
Summary: Python language sdk and tools for Aliyun service api
Home-page: http://www.wantchalk.com
Author: vincent wantchalk
Author-email: ergal@163.com
License: MIT
Keywords: aliyun oss mns
Platform: UNKNOWN
Classifier: Development Status :: 3 - Alpha
Classifier: Intended Audience :: Developers
Classifier: Topic :: Software Development :: Libraries
Classifier: Operating System :: OS Independent
Classifier: License :: OSI Approved :: MIT License
Classifier: Programming Language :: Python :: 2
Classifier: Programming Language :: Python :: 2.6
Classifier: Programming Language :: Python :: 2.7
Classifier: Programming Language :: Python :: 3
Classifier: Programming Language :: Python :: 3.3
Classifier: Programming Language :: Python :: 3.4
Classifier: Programming Language :: Python :: 3.5
